backpack
handler
json_formatter
kitchen_sink_logger
state_manager
