Metadata-Version: 1.1
Name: kitchen-sink-logger
Version: 0.1.6
Summary: Easily log everything, including the kitchen sink, if that's your thing
Home-page: http://packages.python.org/kitchen-sink-logger
Author: Troy Larson
Author-email: troylar@gmail.com
License: MIT
Keywords: logging
Platform: UNKNOWN
Classifier: License :: OSI Approved :: MIT License
